[
  {
    "款号": "BB01",
    "产品图": "=DISPIMG(\"ID_F045D0C5BCD447159BD17FEEF4F46654\",1)",
    "产品名称": "S925 银彩宝耳钉",
    "零售价": 1850,
    "成本价": 212.75
  },
  {
    "款号": "BB02",
    "产品图": "=DISPIMG(\"ID_4C6B80B2241C49CC8841B6861135B90A\",1)",
    "产品名称": "S925 银彩宝耳钉",
    "零售价": 2105,
    "成本价": 242.075
  },
  {
    "款号": "BB03",
    "产品图": "=DISPIMG(\"ID_D9740B82E91A4D0E8E0A364EEA545A29\",1)",
    "产品名称": "S925 银彩宝耳钉",
    "零售价": 1815,
    "成本价": 208.725
  },
  {
    "款号": "BB04",
    "产品图": "=DISPIMG(\"ID_5CF748CC81A845A89CC982499B500948\",1)",
    "产品名称": "S925 银彩宝耳钉",
    "零售价": 1415,
    "成本价": 162.725
  },
  {
    "款号": "BB05",
    "产品图": "=DISPIMG(\"ID_6D716F5553884A7F9D6936F1DDECC0C3\",1)",
    "产品名称": "S925 银彩宝耳钉",
    "零售价": 2110,
    "成本价": 242.65
  },
  {
    "款号": "BB06",
    "产品图": "=DISPIMG(\"ID_3322288D028B4522BC992854CDE854A0\",1)",
    "产品名称": "925 银彩宝项链",
    "零售价": 1975,
    "成本价": 227.125
  },
  {
    "款号": "BB07",
    "产品图": "=DISPIMG(\"ID_92DB779D60EA4B44AECD16A17CD00387\",1)",
    "产品名称": "925 银彩宝项链",
    "零售价": 3125,
    "成本价": 359.375
  },
  {
    "款号": "BB08",
    "产品图": "=DISPIMG(\"ID_7045237F540F4A36812864EFFFFBBCD0\",1)",
    "产品名称": "S925 银彩宝耳钉",
    "零售价": 2005,
    "成本价": 230.575
  },
  {
    "款号": "BB09",
    "产品图": "=DISPIMG(\"ID_9F49FDA29EDD42198E048398BCDA5FAE\",1)",
    "产品名称": "925 银彩宝项链",
    "零售价": 2110,
    "成本价": 242.65
  },
  {
    "款号": "BB10",
    "产品图": "=DISPIMG(\"ID_06C09409870D49DDA1DD2611E9D0D000\",1)",
    "产品名称": "S925 银彩宝耳钉",
    "零售价": 1310,
    "成本价": 150.65
  },
  {
    "款号": "BB11",
    "产品图": "=DISPIMG(\"ID_7FD4A5B810AE425A94D912056297CCB4\",1)",
    "产品名称": "S925 银彩宝耳钉",
    "零售价": 2365,
    "成本价": 271.975
  },
  {
    "款号": "BB12",
    "产品图": "=DISPIMG(\"ID_4727563B1C3F4E1BAF50BEB4C0D9438C\",1)",
    "产品名称": null,
    "零售价": 1790,
    "成本价": 205.85
  },
  {
    "款号": "BB13",
    "产品图": "=DISPIMG(\"ID_A627AC588C8648238379F1675ECEBC3D\",1)",
    "产品名称": null,
    "零售价": 1780,
    "成本价": 204.7
  },
  {
    "款号": "BB14",
    "产品图": "=DISPIMG(\"ID_1E927E8606EC41C8989CA74FAC1E5D62\",1)",
    "产品名称": null,
    "零售价": 1615,
    "成本价": 185.725
  },
  {
    "款号": "BB15",
    "产品图": "=DISPIMG(\"ID_EB83ADC05A5242D994BC32F5696D8D05\",1)",
    "产品名称": null,
    "零售价": 2070,
    "成本价": 238.05
  },
  {
    "款号": "BB16",
    "产品图": "=DISPIMG(\"ID_692718DED7CD4E088FECB81AEEA3DBB2\",1)",
    "产品名称": null,
    "零售价": 2500,
    "成本价": 287.5
  },
  {
    "款号": "BB17",
    "产品图": "=DISPIMG(\"ID_8F045651D67640D691219E71144D0CFF\",1)",
    "产品名称": "S925 银彩宝耳钉",
    "零售价": 1255,
    "成本价": 144.325
  },
  {
    "款号": "BB18",
    "产品图": "=DISPIMG(\"ID_02B859D04F344FD2A4D07A07AC18382C\",1)",
    "产品名称": "S925 银彩宝耳钉",
    "零售价": 1620,
    "成本价": 186.3
  },
  {
    "款号": "BB19",
    "产品图": "=DISPIMG(\"ID_22BFBE025CFF4E9D993472D3D9F7D2CD\",1)",
    "产品名称": "925 银彩宝项链",
    "零售价": 1155,
    "成本价": 132.825
  },
  {
    "款号": "BB20",
    "产品图": "=DISPIMG(\"ID_E3AD1A70CF6D400AB725709628014957\",1)",
    "产品名称": "925 银彩宝项链",
    "零售价": 1980,
    "成本价": 227.7
  },
  {
    "款号": "BB21",
    "产品图": "=DISPIMG(\"ID_279ACF7486324499B3B0FF2E2DDB2FE5\",1)",
    "产品名称": "S925 银彩宝耳钉",
    "零售价": 1865,
    "成本价": 214.475
  },
  {
    "款号": "BB22",
    "产品图": "=DISPIMG(\"ID_E957F103F5CF468597027DEEE5EEB1EB\",1)",
    "产品名称": "925 银彩宝项链",
    "零售价": 1300,
    "成本价": 149.5
  },
  {
    "款号": "BB23",
    "产品图": "=DISPIMG(\"ID_7890DAD97B0C45F4950DD51AF8CB0E9E\",1)",
    "产品名称": "S925 银彩宝耳钉",
    "零售价": 1900,
    "成本价": 218.5
  },
  {
    "款号": "BB24",
    "产品图": "=DISPIMG(\"ID_B3935CF683BB43A59F5D5837B4B8B1AD\",1)",
    "产品名称": "925 银彩宝项链",
    "零售价": 1915,
    "成本价": 220.225
  },
  {
    "款号": "BB25",
    "产品图": "=DISPIMG(\"ID_804A81F1DD7944CB833DA26079B35814\",1)",
    "产品名称": "925 银彩宝项链",
    "零售价": 1535,
    "成本价": 176.525
  },
  {
    "款号": "BB26",
    "产品图": "=DISPIMG(\"ID_32A684218B1641EB87BB7491411F21FA\",1)",
    "产品名称": "925 银彩宝项链",
    "零售价": 1540,
    "成本价": 177.1
  },
  {
    "款号": "BB27",
    "产品图": "=DISPIMG(\"ID_0FBD7D071525419892C8FF678576AA2D\",1)",
    "产品名称": "925 银彩宝项链",
    "零售价": 2215,
    "成本价": 254.725
  },
  {
    "款号": "BB28",
    "产品图": "=DISPIMG(\"ID_A41A94AC80694F94A2F5A66BF7746496\",1)",
    "产品名称": "925 银彩宝项链",
    "零售价": 1960,
    "成本价": 225.4
  },
  {
    "款号": "BB29",
    "产品图": "=DISPIMG(\"ID_1AA8A98DD6864FAFAA49E10C48E38EA2\",1)",
    "产品名称": "925 银彩宝项链",
    "零售价": 1945,
    "成本价": 223.675
  },
  {
    "款号": "BB30",
    "产品图": "=DISPIMG(\"ID_91703B9F0AF144B3987A1EB4F3BF5339\",1)",
    "产品名称": "925 银彩宝项链",
    "零售价": 1980,
    "成本价": 227.7
  },
  {
    "款号": "BB31",
    "产品图": "=DISPIMG(\"ID_56D1E8CF86564C3AAC8B48FAAD27EDC1\",1)",
    "产品名称": null,
    "零售价": 1715,
    "成本价": 197.225
  },
  {
    "款号": "BB32",
    "产品图": "=DISPIMG(\"ID_DD674FCC69244BCDACA19BC60B82340F\",1)",
    "产品名称": null,
    "零售价": 2700,
    "成本价": 310.5
  },
  {
    "款号": "BB33",
    "产品图": "=DISPIMG(\"ID_43240049776242F0B327952E6E84CD5C\",1)",
    "产品名称": null,
    "零售价": 1200,
    "成本价": 138
  },
  {
    "款号": "BB34",
    "产品图": "=DISPIMG(\"ID_0E581B7253DE415EA7A774A7C6269259\",1)",
    "产品名称": null,
    "零售价": 3015,
    "成本价": 346.725
  },
  {
    "款号": "BB35",
    "产品图": "=DISPIMG(\"ID_8852E2878F1B4757A1F8AFCDD465EEA8\",1)",
    "产品名称": null,
    "零售价": 2220,
    "成本价": 255.3
  },
  {
    "款号": "BB36",
    "产品图": "=DISPIMG(\"ID_B0528D7ED7CC42E3B34EA10B856FC53B\",1)",
    "产品名称": null,
    "零售价": 2130,
    "成本价": 244.95
  },
  {
    "款号": "BB37",
    "产品图": "=DISPIMG(\"ID_6645CD042C3F42AD95B610BDF0F7AF9B\",1)",
    "产品名称": null,
    "零售价": 1300,
    "成本价": 149.5
  },
  {
    "款号": "BB38",
    "产品图": "=DISPIMG(\"ID_61E01E7DF5E04248B799A1CECD67F2C3\",1)",
    "产品名称": null,
    "零售价": 2145,
    "成本价": 246.675
  },
  {
    "款号": "BB39",
    "产品图": "=DISPIMG(\"ID_84B8D489CFE9402FA71B985C31BD64F5\",1)",
    "产品名称": null,
    "零售价": 1255,
    "成本价": 144.325
  },
  {
    "款号": "BB40",
    "产品图": "=DISPIMG(\"ID_6327C21B61344FCD80E6E1CE2F8798D3\",1)",
    "产品名称": null,
    "零售价": 3040,
    "成本价": 349.6
  },
  {
    "款号": "BB41",
    "产品图": "=DISPIMG(\"ID_806B96E6C7494BD5A32A552EDCAF3825\",1)",
    "产品名称": null,
    "零售价": 2725,
    "成本价": 313.375
  },
  {
    "款号": "BB42",
    "产品图": "=DISPIMG(\"ID_37513961B63740D097B1733F7DE88160\",1)",
    "产品名称": "925 银彩宝项链",
    "零售价": 1915,
    "成本价": 220.225
  },
  {
    "款号": "BB43",
    "产品图": "=DISPIMG(\"ID_EE704DE4A2834E2B99F423FCE264FDB8\",1)",
    "产品名称": "925 银彩宝项链",
    "零售价": 1980,
    "成本价": 227.7
  },
  {
    "款号": "BB44",
    "产品图": "=DISPIMG(\"ID_22DD9485E41E4C4983BBEA67429AE9EB\",1)",
    "产品名称": "S925 银彩宝耳钉",
    "零售价": 1310,
    "成本价": 150.65
  },
  {
    "款号": "BB45",
    "产品图": "=DISPIMG(\"ID_7E15D369D26D4314B2D48809DED73A24\",1)",
    "产品名称": null,
    "零售价": 1650,
    "成本价": 189.75
  },
  {
    "款号": "BB46",
    "产品图": "=DISPIMG(\"ID_546CBE78826D43069A2D2A9661D63B49\",1)",
    "产品名称": null,
    "零售价": 2380,
    "成本价": 273.7
  },
  {
    "款号": "BB47",
    "产品图": "=DISPIMG(\"ID_1B2E4B78390842DF86DC44D235192F2E\",1)",
    "产品名称": null,
    "零售价": 1255,
    "成本价": 144.325
  },
  {
    "款号": "BB48",
    "产品图": "=DISPIMG(\"ID_7DCC57327EDF4687ACEE8141EAC58EEC\",1)",
    "产品名称": "S925 银彩宝耳钉",
    "零售价": 2065,
    "成本价": 237.475
  },
  {
    "款号": "BB49",
    "产品图": "=DISPIMG(\"ID_20E815286DD443ADB163EE43A3129EF7\",1)",
    "产品名称": null,
    "零售价": 1880,
    "成本价": 216.2
  },
  {
    "款号": "BB50",
    "产品图": "=DISPIMG(\"ID_178A6B1B910D4541B9AC1EFBD45F723D\",1)",
    "产品名称": null,
    "零售价": 1150,
    "成本价": 132.25
  },
  {
    "款号": "BB51",
    "产品图": "=DISPIMG(\"ID_779E33341DFA4DABB5F9AE235D7DD82A\",1)",
    "产品名称": null,
    "零售价": 1450,
    "成本价": 166.75
  },
  {
    "款号": "BB52",
    "产品图": "=DISPIMG(\"ID_5AA97705B87B45E4B7C8CF5B393ACBBA\",1)",
    "产品名称": null,
    "零售价": 1800,
    "成本价": 207
  },
  {
    "款号": "BB53",
    "产品图": "=DISPIMG(\"ID_B02257C00E824CC2ADD73EFA0F3E7A90\",1)",
    "产品名称": "圆粉耳钉",
    "零售价": 1575,
    "成本价": 181.125
  },
  {
    "款号": "BB54",
    "产品图": "=DISPIMG(\"ID_EE51E3C4B1644EECAC8B444882FFD86F\",1)",
    "产品名称": "圆蓝耳钉",
    "零售价": 1330,
    "成本价": 152.95
  },
  {
    "款号": "BB55",
    "产品图": "=DISPIMG(\"ID_F0D913EE026E481E8778A1717D8AF28B\",1)",
    "产品名称": "圆黄戒指",
    "零售价": 1505,
    "成本价": 173.075
  },
  {
    "款号": "BB56",
    "产品图": "=DISPIMG(\"ID_800B0829728645F4A30D7E19B4D91E92\",1)",
    "产品名称": "圆粉耳钉",
    "零售价": 1070,
    "成本价": 123.05
  },
  {
    "款号": "BB57",
    "产品图": "=DISPIMG(\"ID_BB3CCFFF60804FAF93BE10E899B99A57\",1)",
    "产品名称": "圆粉戒指",
    "零售价": 1205,
    "成本价": 138.575
  },
  {
    "款号": "BB58",
    "产品图": "=DISPIMG(\"ID_90D774ABABAF4AA9A5E19F1C2CF67388\",1)",
    "产品名称": "方粉戒指",
    "零售价": 1640,
    "成本价": 188.6
  },
  {
    "款号": "BB59",
    "产品图": "=DISPIMG(\"ID_01A96DE5FCF745CFBD176825632B4A3F\",1)",
    "产品名称": "方粉耳钉",
    "零售价": 1455,
    "成本价": 167.325
  },
  {
    "款号": "BB60",
    "产品图": "=DISPIMG(\"ID_897786F25C5847B79E103798DE37A882\",1)",
    "产品名称": "圆粉项链",
    "零售价": 1110,
    "成本价": 127.65
  },
  {
    "款号": "BB61",
    "产品图": "=DISPIMG(\"ID_F466C2C7B19145BB9F71395B72C271F2\",1)",
    "产品名称": "方粉项链",
    "零售价": 1245,
    "成本价": 143.175
  },
  {
    "款号": "BB62",
    "产品图": "=DISPIMG(\"ID_8D9C8376730A434AAE162470B09E5863\",1)",
    "产品名称": "方粉戒指",
    "零售价": 1273,
    "成本价": 146.395
  },
  {
    "款号": "BB63",
    "产品图": "=DISPIMG(\"ID_7AC7BBB8A6304254853D1BB6E7366DFE\",1)",
    "产品名称": "圆黄戒指",
    "零售价": 1255,
    "成本价": 144.325
  },
  {
    "款号": "BB64",
    "产品图": "=DISPIMG(\"ID_41245E3B56394136903093D3B1A96FBA\",1)",
    "产品名称": "圆蓝耳钉",
    "零售价": 2030,
    "成本价": 233.45
  },
  {
    "款号": "BB65",
    "产品图": "=DISPIMG(\"ID_64099746DEAD4999A5A270A6F60FFC69\",1)",
    "产品名称": "碎钻手链",
    "零售价": 945,
    "成本价": 108.675
  },
  {
    "款号": "BB66",
    "产品图": "=DISPIMG(\"ID_2AA21CF62EA54B3E921DCAA5D6324754\",1)",
    "产品名称": "圆蓝戒指",
    "零售价": 1380,
    "成本价": 158.7
  },
  {
    "款号": "BB67",
    "产品图": "=DISPIMG(\"ID_69C9F2C647ED4512B73D457C8B2D7DA3\",1)",
    "产品名称": "碎钻耳环",
    "零售价": 890,
    "成本价": 102.35
  },
  {
    "款号": "BB68",
    "产品图": "=DISPIMG(\"ID_7D1F2BEE3B0440BBA7F1AE6B3BBCE1B9\",1)",
    "产品名称": "大钻手链",
    "零售价": 965,
    "成本价": 110.975
  },
  {
    "款号": "BB69",
    "产品图": "=DISPIMG(\"ID_0BD78C866B434B7E800D2717D03C3EE1\",1)",
    "产品名称": "红钻手链",
    "零售价": 3600,
    "成本价": 414
  },
  {
    "款号": "BB70",
    "产品图": "=DISPIMG(\"ID_14B69789212C4781933775C747D5DB77\",1)",
    "产品名称": "蓝钻手链",
    "零售价": 3600,
    "成本价": 414
  },
  {
    "款号": "BB71",
    "产品图": "=DISPIMG(\"ID_FC42C0FDA9F6418783781DF776E1A00B\",1)",
    "产品名称": "绿钻手链",
    "零售价": 3600,
    "成本价": 414
  },
  {
    "款号": "BB72",
    "产品图": "=DISPIMG(\"ID_239274254D424BB9B5B7CB76A372AC75\",1)",
    "产品名称": "大钻项链",
    "零售价": 965,
    "成本价": 110.975
  },
  {
    "款号": "BB73",
    "产品图": "=DISPIMG(\"ID_2FF5E4BBC629460D9D822A882F778AB6\",1)",
    "产品名称": "1卡耳钉",
    "零售价": 735,
    "成本价": 84.525
  },
  {
    "款号": "BB74",
    "产品图": "=DISPIMG(\"ID_8C66062718A14FB69941A75A3A7550B8\",1)",
    "产品名称": "碎钻项链",
    "零售价": 1285,
    "成本价": 147.775
  },
  {
    "款号": "BB75",
    "产品图": "=DISPIMG(\"ID_FBC59B679390459192A26FC01CA9704E\",1)",
    "产品名称": "1卡手链",
    "零售价": 750,
    "成本价": 86.25
  },
  {
    "款号": "BB76",
    "产品图": "=DISPIMG(\"ID_ADF31246086C48DA882C3191629F9A51\",1)",
    "产品名称": "2卡戒指",
    "零售价": 1205,
    "成本价": 138.575
  },
  {
    "款号": "BB77",
    "产品图": "=DISPIMG(\"ID_97EC23446F02444B9ED1075D3F8E997C\",1)",
    "产品名称": "3卡戒指",
    "零售价": 1295,
    "成本价": 148.925
  },
  {
    "款号": "BB78",
    "产品图": "=DISPIMG(\"ID_E0F689253F9847A18FBCFA73266FA04B\",1)",
    "产品名称": "2卡戒指",
    "零售价": 1220,
    "成本价": 140.3
  },
  {
    "款号": "BB79",
    "产品图": "=DISPIMG(\"ID_545F4CB24B9B4FF59E65AE3698B702FE\",1)",
    "产品名称": "1卡项链",
    "零售价": 1136,
    "成本价": 130.64
  },
  {
    "款号": "BB80",
    "产品图": "=DISPIMG(\"ID_8B7EB80C5ABD4CE4A45E0C43F996144D\",1)",
    "产品名称": "1卡戒指",
    "零售价": 1045,
    "成本价": 120.175
  },
  {
    "款号": "BB81",
    "产品图": "=DISPIMG(\"ID_99D1BBA6C97241538DA9A7B92507D5BC\",1)",
    "产品名称": "2卡耳钉",
    "零售价": 1100,
    "成本价": 126.5
  },
  {
    "款号": "BB82",
    "产品图": "=DISPIMG(\"ID_5DE0581B90FA4D41B176810F920EC5BD\",1)",
    "产品名称": "2卡戒指",
    "零售价": 1245,
    "成本价": 143.175
  },
  {
    "款号": "BB83",
    "产品图": "=DISPIMG(\"ID_CE93AD48CCCC476DA717091D329FFE28\",1)",
    "产品名称": "2卡项链",
    "零售价": 1355,
    "成本价": 155.825
  },
  {
    "款号": "BB84",
    "产品图": "=DISPIMG(\"ID_95A2920467DE43D0A1C8EBCD0364E88D\",1)",
    "产品名称": "2卡戒指",
    "零售价": 1505,
    "成本价": 173.075
  },
  {
    "款号": "BB85",
    "产品图": "=DISPIMG(\"ID_9C1ABBF584BF4DB3AAAE97CAA7BF00A2\",1)",
    "产品名称": "2卡戒指",
    "零售价": 1220,
    "成本价": 140.3
  },
  {
    "款号": "BB86",
    "产品图": "=DISPIMG(\"ID_F276907954B84BBF928D0A2E14A6FC59\",1)",
    "产品名称": "50分耳钉",
    "零售价": 930,
    "成本价": 106.95
  },
  {
    "款号": "BB87",
    "产品图": "=DISPIMG(\"ID_94704FC28294497FBE982E584075605C\",1)",
    "产品名称": "碎钻戒指",
    "零售价": 860,
    "成本价": 98.9
  },
  {
    "款号": "BB88",
    "产品图": "=DISPIMG(\"ID_2005808BA2CA46E3AE3B3E5E715B2FC0\",1)",
    "产品名称": "1卡戒指",
    "零售价": 1135,
    "成本价": 130.525
  },
  {
    "款号": "BB89",
    "产品图": "=DISPIMG(\"ID_F86DEB087F2D42DA909950BA722A036A\",1)",
    "产品名称": "1卡项链",
    "零售价": 1050,
    "成本价": 120.75
  },
  {
    "款号": "BB90",
    "产品图": "=DISPIMG(\"ID_98E385758198452485FD079E64B126E7\",1)",
    "产品名称": "1卡戒指",
    "零售价": 805,
    "成本价": 92.575
  },
  {
    "款号": "BB91",
    "产品图": "=DISPIMG(\"ID_F7E48E1E8C6647E7AC40262DCA929853\",1)",
    "产品名称": "1卡耳钉",
    "零售价": 825,
    "成本价": 94.875
  },
  {
    "款号": "BB92",
    "产品图": "=DISPIMG(\"ID_6AD4A0D9B8E84069AB861564AA6EB611\",1)",
    "产品名称": "2卡戒指",
    "零售价": 1340,
    "成本价": 154.1
  },
  {
    "款号": "BB93",
    "产品图": "=DISPIMG(\"ID_B1BE78B7956645919167F4B689B8CB3D\",1)",
    "产品名称": "2卡戒指",
    "零售价": 1140,
    "成本价": 131.1
  }
]